mvg_console/__init__.py
mvg_console/departure.py
mvg_console/example.py
mvg_console/history_manager.py
mvg_console/main.py
mvg_console-2021.2.12.dist-info/LICENSE
mvg_console-2021.2.12.dist-info/METADATA
mvg_console-2021.2.12.dist-info/WHEEL
mvg_console-2021.2.12.dist-info/entry_points.txt
mvg_console-2021.2.12.dist-info/top_level.txt
mvg_console-2021.2.12.dist-info/RECORD
