Metadata-Version: 2.1
Name: mvg-console
Version: 2021.2.12
Summary: A Command Line Tool to get the MVG departures for a station.
Home-page: https://github.com/aadhithya/mvg_console
Author: Aadhithya Sankar, Frank Lu
License: UNKNOWN
Platform: UNKNOWN
Classifier: Environment :: Console
Classifier: Programming Language :: Python :: 3.6
Classifier: Development Status :: 5 - Production/Stable
Classifier: Intended Audience :: End Users/Desktop
Classifier: License :: OSI Approved :: MIT License
Classifier: Programming Language :: Python :: 3 :: Only
Classifier: Topic :: Utilities
Requires-Python: >=3.6
Requires-Dist: requests
Requires-Dist: colr
Requires-Dist: prettytable
